shibamysql/__init__.py
shibamysql/database.py
shibamysql/missing_data_error.py
shibamysql/query_builder.py
shibamysql/table_builder.py
shiba_mysql-1.2.0.dist-info/LICENSE
shiba_mysql-1.2.0.dist-info/METADATA
shiba_mysql-1.2.0.dist-info/WHEEL
shiba_mysql-1.2.0.dist-info/top_level.txt
shiba_mysql-1.2.0.dist-info/RECORD
