Metadata-Version: 2.1
Name: shiba-mysql
Version: 1.2.0
Summary: A library to interact with MySQL
Home-page: https://github.com/ShibaRoPinoo/Shiba-Py-Mysql
Author: Rodrigo Pino
Author-email: ro.pinoo18@gmail.com
License: MIT
Keywords: mysql,database,SQL,data access,ORM
Classifier: License :: OSI Approved :: MIT License
Classifier: Programming Language :: Python :: 3.7
Classifier: Programming Language :: Python :: 3.8
Classifier: Programming Language :: Python :: 3.9
Classifier: Programming Language :: Python :: 3.10
Classifier: Topic :: Database
Classifier: Topic :: Software Development
Classifier: Topic :: Software Development :: Libraries
Classifier: Topic :: Software Development :: Libraries :: Python Modules
License-File: LICENSE
Requires-Dist: pymysql
